{"Player.PlayerController":{"Level":1,"Money":9900.0,"Experience":0,"Posx":21.4760761,"Posy":-0.669875145},"InventorySystem.BagsManager":[{"ID":"SeedCarrot","Quantity":1,"Durability":0,"IsStackABle":true}],"InventorySystem.Inventory":[],"MissionSystem.QuestManager":{"HarvestAnimal":{"IdMission":"HarvestAnimal","CurrentCount":0,"IsDone":false},"HarvestCarrot":{"IdMission":"HarvestCarrot","CurrentCount":0,"IsDone":false}},"LandManager":{"Item1":{"0":{"LandState":"soildefaut","LastWatered":{"year":0,"season":0,"day":0,"hour":0,"minute":0,"second":0},"IsPlanted":false},"1":{"LandState":"soildefaut","LastWatered":{"year":0,"season":0,"day":0,"hour":0,"minute":0,"second":0},"IsPlanted":false},"2":{"LandState":"soildefaut","LastWatered":{"year":0,"season":0,"day":0,"hour":0,"minute":0,"second":0},"IsPlanted":false},"3":{"LandState":"soildefaut","LastWatered":{"year":0,"season":0,"day":0,"hour":0,"minute":0,"second":0},"IsPlanted":false},"4":{"LandState":"soildefaut","LastWatered":{"year":0,"season":0,"day":0,"hour":0,"minute":0,"second":0},"IsPlanted":false},"5":{"LandState":"soildefaut","LastWatered":{"year":0,"season":0,"day":0,"hour":0,"minute":0,"second":0},"IsPlanted":false},"6":{"LandState":"soildefaut","LastWatered":{"year":0,"season":0,"day":0,"hour":0,"minute":0,"second":0},"IsPlanted":false},"7":{"LandState":"soildefaut","LastWatered":{"year":0,"season":0,"day":0,"hour":0,"minute":0,"second":0},"IsPlanted":false},"8":{"LandState":"soildefaut","LastWatered":{"year":0,"season":0,"day":0,"hour":0,"minute":0,"second":0},"IsPlanted":false},"9":{"LandState":"soildefaut","LastWatered":{"year":0,"season":0,"day":0,"hour":0,"minute":0,"second":0},"IsPlanted":false},"10":{"LandState":"soildefaut","LastWatered":{"year":0,"season":0,"day":0,"hour":0,"minute":0,"second":0},"IsPlanted":false},"11":{"LandState":"soildefaut","LastWatered":{"year":0,"season":0,"day":0,"hour":0,"minute":0,"second":0},"IsPlanted":false},"12":{"LandState":"soildefaut","LastWatered":{"year":0,"season":0,"day":0,"hour":0,"minute":0,"second":0},"IsPlanted":false},"13":{"LandState":"soildefaut","LastWatered":{"year":0,"season":0,"day":0,"hour":0,"minute":0,"second":0},"IsPlanted":false},"14":{"LandState":"soildefaut","LastWatered":{"year":0,"season":0,"day":0,"hour":0,"minute":0,"second":0},"IsPlanted":false},"15":{"LandState":"soildefaut","LastWatered":{"year":0,"season":0,"day":0,"hour":0,"minute":0,"second":0},"IsPlanted":false},"16":{"LandState":"soildefaut","LastWatered":{"year":0,"season":0,"day":0,"hour":0,"minute":0,"second":0},"IsPlanted":false},"17":{"LandState":"soildefaut","LastWatered":{"year":0,"season":0,"day":0,"hour":0,"minute":0,"second":0},"IsPlanted":false},"18":{"LandState":"soildefaut","LastWatered":{"year":0,"season":0,"day":0,"hour":0,"minute":0,"second":0},"IsPlanted":false},"19":{"LandState":"soildefaut","LastWatered":{"year":0,"season":0,"day":0,"hour":0,"minute":0,"second":0},"IsPlanted":false},"20":{"LandState":"soildefaut","LastWatered":{"year":0,"season":0,"day":0,"hour":0,"minute":0,"second":0},"IsPlanted":false},"21":{"LandState":"soildefaut","LastWatered":{"year":0,"season":0,"day":0,"hour":0,"minute":0,"second":0},"IsPlanted":false},"22":{"LandState":"soildefaut","LastWatered":{"year":0,"season":0,"day":0,"hour":0,"minute":0,"second":0},"IsPlanted":false},"23":{"LandState":"soildefaut","LastWatered":{"year":0,"season":0,"day":0,"hour":0,"minute":0,"second":0},"IsPlanted":false},"24":{"LandState":"soildefaut","LastWatered":{"year":0,"season":0,"day":0,"hour":0,"minute":0,"second":0},"IsPlanted":false},"25":{"LandState":"soildefaut","LastWatered":{"year":0,"season":0,"day":0,"hour":0,"minute":0,"second":0},"IsPlanted":false},"26":{"LandState":"soildefaut","LastWatered":{"year":0,"season":0,"day":0,"hour":0,"minute":0,"second":0},"IsPlanted":false}},"Item2":{}},"CowStable":[]}